depixelate.py
gaussian.py
lut.py
shape.py
depixelate-1.0.6.dist-info/LICENCE
depixelate-1.0.6.dist-info/METADATA
depixelate-1.0.6.dist-info/WHEEL
depixelate-1.0.6.dist-info/top_level.txt
depixelate-1.0.6.dist-info/RECORD
