Metadata-Version: 2.1
Name: depixelate
Version: 1.0.6
Summary: Depixelate images
Home-page: UNKNOWN
Author: Vilmacio M. Silva
License: UNKNOWN
Platform: UNKNOWN
Classifier: Programming Language :: Python :: 3
Classifier: License :: OSI Approved :: MIT License
Classifier: Operating System :: OS Independent
Requires-Python: >=3.6
License-File: LICENCE
Requires-Dist: opencv-python
Requires-Dist: numpy
Requires-Dist: pytest
Requires-Dist: Pillow
